CjyLoveWfy/__init__.py
CjyLoveWfy/background.jpg
CjyLoveWfy/crash.wav
CjyLoveWfy/font.ttf
CjyLoveWfy/kaiti.ttf
CjyLoveWfy/main.py
CjyLoveWfy/racecar.jpg
CjyLoveWfy/racestart.wav
CjyLoveWfy/tiantiande.wav
CjyLoveWfy/photos/1.jpg
CjyLoveWfy/photos/10.jpg
CjyLoveWfy/photos/11.jpg
CjyLoveWfy/photos/12.jpg
CjyLoveWfy/photos/13.jpg
CjyLoveWfy/photos/14.jpg
CjyLoveWfy/photos/15.jpg
CjyLoveWfy/photos/2.jpg
CjyLoveWfy/photos/3.jpg
CjyLoveWfy/photos/4.jpg
CjyLoveWfy/photos/5.jpg
CjyLoveWfy/photos/6.jpg
CjyLoveWfy/photos/7.jpg
CjyLoveWfy/photos/70.jpg
CjyLoveWfy/photos/8.jpg
CjyLoveWfy/photos/9.jpg
CjyLoveWfy-0.0.1.dist-info/LICENSE
CjyLoveWfy-0.0.1.dist-info/METADATA
CjyLoveWfy-0.0.1.dist-info/WHEEL
CjyLoveWfy-0.0.1.dist-info/top_level.txt
CjyLoveWfy-0.0.1.dist-info/RECORD
